darca_space_git/__init__.py
darca_space_git/__version__.py
darca_space_git/exceptions.py
darca_space_git/space_git.py
darca_space_git-0.1.0.dist-info/LICENSE
darca_space_git-0.1.0.dist-info/METADATA
darca_space_git-0.1.0.dist-info/WHEEL
darca_space_git-0.1.0.dist-info/RECORD
