Metadata-Version: 2.3
Name: darca-space-git
Version: 0.1.0
Summary: Git manager for repositories in darca spaces.
License: LICENSE
Author: Roel Kist
Author-email: roel.kist@gmail.com
Requires-Python: >=3.12,<4.0
Classifier: License :: Other/Proprietary License
Classifier: Programming Language :: Python :: 3
Classifier: Programming Language :: Python :: 3.12
Classifier: Programming Language :: Python :: 3.13
Requires-Dist: darca-exception (>=0.1.0,<0.2.0)
Requires-Dist: darca-git (>=0.1.0,<0.2.0)
Requires-Dist: darca-log-facility (>=0.1.0,<0.2.0)
Requires-Dist: darca-space-manager (>=0.3.0,<0.4.0)
